clouddiscovery/__init__.py
clouddiscovery/pathmagic.py
clouddiscovery/commands/__init__.py
clouddiscovery/locales/__init__.py
clouddiscovery/locales/en_US/__init__.py
clouddiscovery/locales/en_US/LC_MESSAGES/__init__.py
clouddiscovery/locales/en_US/LC_MESSAGES/messages.mo
clouddiscovery/locales/pt_BR/__init__.py
clouddiscovery/locales/pt_BR/LC_MESSAGES/__init__.py
clouddiscovery/locales/pt_BR/LC_MESSAGES/messages.mo
clouddiscovery/provider/__init__.py
clouddiscovery/provider/iot/__init__.py
clouddiscovery/provider/iot/command.py
clouddiscovery/provider/iot/diagram.py
clouddiscovery/provider/iot/resource/__init__.py
clouddiscovery/provider/iot/resource/certificate.py
clouddiscovery/provider/iot/resource/policy.py
clouddiscovery/provider/iot/resource/thing.py
clouddiscovery/provider/policy/__init__.py
clouddiscovery/provider/policy/command.py
clouddiscovery/provider/policy/resource/__init__.py
clouddiscovery/provider/policy/resource/general.py
clouddiscovery/provider/policy/resource/security.py
clouddiscovery/provider/vpc/__init__.py
clouddiscovery/provider/vpc/command.py
clouddiscovery/provider/vpc/diagram.py
clouddiscovery/provider/vpc/resource/__init__.py
clouddiscovery/provider/vpc/resource/analytics.py
clouddiscovery/provider/vpc/resource/application.py
clouddiscovery/provider/vpc/resource/compute.py
clouddiscovery/provider/vpc/resource/containers.py
clouddiscovery/provider/vpc/resource/database.py
clouddiscovery/provider/vpc/resource/management.py
clouddiscovery/provider/vpc/resource/mediaservices.py
clouddiscovery/provider/vpc/resource/network.py
clouddiscovery/provider/vpc/resource/security.py
clouddiscovery/provider/vpc/resource/storage.py
clouddiscovery/shared/__init__.py
clouddiscovery/shared/command.py
clouddiscovery/shared/common.py
clouddiscovery/shared/diagram.py
clouddiscovery/shared/error_handler.py
clouddiscovery/shared/report.py
clouddiscovery/tests/__init__.py
clouddiscovery-2.0.508.data/scripts/clouddiscovery
clouddiscovery-2.0.508.dist-info/LICENSE
clouddiscovery-2.0.508.dist-info/METADATA
clouddiscovery-2.0.508.dist-info/WHEEL
clouddiscovery-2.0.508.dist-info/top_level.txt
clouddiscovery-2.0.508.dist-info/RECORD
