Metadata-Version: 2.1
Name: clouddiscovery
Version: 2.0.508
Summary: The tool to help you discover resources in the cloud environment
Home-page: https://github.com/Cloud-Architects/cloud-discovery
Author: Cloud Architects
License: Apache License 2.0
Platform: UNKNOWN
Classifier: Development Status :: 5 - Production/Stable
Classifier: Environment :: Console
Classifier: Intended Audience :: System Administrators
Classifier: Natural Language :: English
Classifier: License :: OSI Approved :: Apache Software License
Classifier: Programming Language :: Python
Classifier: Programming Language :: Python :: 3.6
Classifier: Programming Language :: Python :: 3.7
Classifier: Programming Language :: Python :: 3.8
Requires-Python: >=3.6
Requires-Dist: boto3
Requires-Dist: ipaddress
Requires-Dist: diagrams (>=0.13)
